openfed_mmlab/__init__.py
openfed_mmlab-0.0.0rc0.dist-info/LICENSE
openfed_mmlab-0.0.0rc0.dist-info/METADATA
openfed_mmlab-0.0.0rc0.dist-info/WHEEL
openfed_mmlab-0.0.0rc0.dist-info/top_level.txt
openfed_mmlab-0.0.0rc0.dist-info/RECORD
